miservice/__init__.py
miservice/__main__.py
miservice/cli.py
miservice/miaccount.py
miservice/miiocommand.py
miservice/miioservice.py
miservice/minaservice.py
miservice_fork-2.9.0.data/scripts/micli.py
miservice_fork-2.9.0.dist-info/licenses/LICENSE
miservice_fork-2.9.0.dist-info/METADATA
miservice_fork-2.9.0.dist-info/WHEEL
miservice_fork-2.9.0.dist-info/entry_points.txt
miservice_fork-2.9.0.dist-info/top_level.txt
miservice_fork-2.9.0.dist-info/RECORD
