Metadata-Version: 2.4
Name: miservice_fork
Version: 2.9.0
Summary: XiaoMi Cloud Service fork from https://github.com/Yonsm/MiService
Home-page: https://github.com/yihong0618/MiService
Author: Yonsm, yihong0618
Author-email: Yonsm@qq.com, zouzou0208@gmail.com
License: MIT
Classifier: Programming Language :: Python :: 3
Classifier: License :: OSI Approved :: MIT License
Classifier: Operating System :: OS Independent
Requires-Python: >=3.8
License-File: LICENSE
Requires-Dist: aiohttp
Requires-Dist: mutagen
Requires-Dist: rich
Dynamic: author
Dynamic: author-email
Dynamic: classifier
Dynamic: home-page
Dynamic: license
Dynamic: license-file
Dynamic: requires-dist
Dynamic: requires-python
Dynamic: summary
